reldi_tokeniser/__init__.py
reldi_tokeniser/bg.abbrev
reldi_tokeniser/hr.abbrev
reldi_tokeniser/mk.abbrev
reldi_tokeniser/punct
reldi_tokeniser/sl.abbrev
reldi_tokeniser/sr.abbrev
reldi_tokeniser/tokeniser.py
reldi_tokeniser-1.0.3.dist-info/LICENSE
reldi_tokeniser-1.0.3.dist-info/METADATA
reldi_tokeniser-1.0.3.dist-info/WHEEL
reldi_tokeniser-1.0.3.dist-info/top_level.txt
reldi_tokeniser-1.0.3.dist-info/RECORD
