Metadata-Version: 2.1
Name: reldi-tokeniser
Version: 1.0.3
Summary: Sentence splitting and tokenization for South Slavic languages
Home-page: https://www.github.com/clarinsi/reldi-tokeniser
Author: CLARIN.SI
License: apache-2.0
License-File: LICENSE
